Callue/__init__.py
Callue/_app.py
Callue/default_routes.py
Callue/routemap.py
Callue/util.py
callue-1.0.0.dist-info/LICENSE
callue-1.0.0.dist-info/WHEEL
callue-1.0.0.dist-info/METADATA
callue-1.0.0.dist-info/RECORD
