Metadata-Version: 2.1
Name: callue
Version: 1.0.0
Summary: A webserver preprocessor of sorts
Author: Callum
Author-email: callum@jcwyt.com
Requires-Python: >=3.8.0,<3.9
Classifier: Programming Language :: Python :: 3
Classifier: Programming Language :: Python :: 3.8
Requires-Dist: Paste (>=3.5.0,<4.0.0)
Requires-Dist: bottle (>=0.12.19,<0.13.0)
Requires-Dist: htmlmin (>=0.1.12,<0.2.0)
Requires-Dist: jsmin (>=3.0.1,<4.0.0)
Requires-Dist: numpy (>=1.22.2,<2.0.0)
Requires-Dist: rcssmin (>=1.1.0,<2.0.0)
